{
  "metadata": {
    "generated_at": "2025-07-21T15:14:27",
    "model_used": "./scripts/cross_refs/t5-mlsys-domain-adapted/",
    "model_type": "Domain-adapted",
    "total_sections": 741,
    "total_cross_references": 66,
    "approach": "domain_adapted_t5"
  },
  "cross_references": [
    {
      "file": "introduction.qmd",
      "sections": [
        {
          "section_id": "sec-introduction-ai-ml-basics-041a",
          "section_title": "AI and ML Basics",
          "targets": [
            {
              "target_section_id": "sec-conclusion-ai-system-efficiency-b9e5",
              "target_section_title": "AI System Efficiency",
              "connection_type": "Preview",
              "similarity": 0.8432511687278748
            }
          ]
        },
        {
          "section_id": "sec-introduction-ai-evolution-0dd8",
          "section_title": "AI Evolution",
          "targets": [
            {
              "target_section_id": "sec-conclusion-congratulations-9028",
              "target_section_title": "Congratulations",
              "connection_type": "Preview",
              "similarity": 0.8028408885002136
            }
          ]
        },
        {
          "section_id": "sec-introduction-deep-learning-era-bd1a",
          "section_title": "Deep Learning Era",
          "targets": [
            {
              "target_section_id": "sec-conclusion-future-ml-systems-13b5",
              "target_section_title": "Future of ML Systems",
              "connection_type": "Preview",
              "similarity": 0.8374710083007812
            }
          ]
        },
        {
          "section_id": "sec-introduction-defining-ml-systems-8f42",
          "section_title": "Defining ML Systems",
          "targets": [
            {
              "target_section_id": "sec-conclusion-ml-dataset-importance-e1af",
              "target_section_title": "ML Dataset Importance",
              "connection_type": "Preview",
              "similarity": 0.7775523662567139
            }
          ]
        },
        {
          "section_id": "sec-introduction-ml-systems-wild-e270",
          "section_title": "ML Systems in the Wild",
          "targets": [
            {
              "target_section_id": "sec-conclusion-future-ml-systems-13b5",
              "target_section_title": "Future of ML Systems",
              "connection_type": "Preview",
              "similarity": 0.8396445512771606
            }
          ]
        },
        {
          "section_id": "sec-introduction-ml-systems-impact-lifecycle-f5f9",
          "section_title": "ML Systems Impact on Lifecycle",
          "targets": [
            {
              "target_section_id": "sec-ml-systems-system-principles-layer-7ed6",
              "target_section_title": "System Principles Layer",
              "connection_type": "Preview",
              "similarity": 0.8585700392723083
            },
            {
              "target_section_id": "sec-conclusion-ethical-considerations-0219",
              "target_section_title": "Ethical Considerations",
              "connection_type": "Preview",
              "similarity": 0.8562028408050537
            },
            {
              "target_section_id": "sec-conclusion-ai-hardware-advancements-9fdf",
              "target_section_title": "AI Hardware Advancements",
              "connection_type": "Preview",
              "similarity": 0.8534669876098633
            }
          ]
        },
        {
          "section_id": "sec-introduction-practical-applications-cd2d",
          "section_title": "Practical Applications",
          "targets": [
            {
              "target_section_id": "sec-conclusion-ethical-considerations-0219",
              "target_section_title": "Ethical Considerations",
              "connection_type": "Preview",
              "similarity": 0.8582897782325745
            }
          ]
        },
        {
          "section_id": "sec-introduction-challenges-ml-systems-f08f",
          "section_title": "Challenges in ML Systems",
          "targets": [
            {
              "target_section_id": "sec-conclusion-security-privacy-a32e",
              "target_section_title": "Security and Privacy",
              "connection_type": "Preview",
              "similarity": 0.8218479752540588
            }
          ]
        },
        {
          "section_id": "sec-introduction-datarelated-challenges-5b58",
          "section_title": "Data-Related Challenges",
          "targets": [
            {
              "target_section_id": "sec-conclusion-future-ml-systems-13b5",
              "target_section_title": "Future of ML Systems",
              "connection_type": "Preview",
              "similarity": 0.9257386922836304
            },
            {
              "target_section_id": "sec-conclusion-ethical-considerations-0219",
              "target_section_title": "Ethical Considerations",
              "connection_type": "Preview",
              "similarity": 0.900916576385498
            }
          ]
        },
        {
          "section_id": "sec-introduction-modelrelated-challenges-ae5a",
          "section_title": "Model-Related Challenges",
          "targets": [
            {
              "target_section_id": "sec-conclusion-future-ml-systems-13b5",
              "target_section_title": "Future of ML Systems",
              "connection_type": "Preview",
              "similarity": 0.8623257875442505
            },
            {
              "target_section_id": "sec-conclusion-ml-training-basics-30d3",
              "target_section_title": "ML Training Basics",
              "connection_type": "Preview",
              "similarity": 0.8597884774208069
            },
            {
              "target_section_id": "sec-conclusion-ai-hardware-advancements-9fdf",
              "target_section_title": "AI Hardware Advancements",
              "connection_type": "Preview",
              "similarity": 0.8567101359367371
            }
          ]
        },
        {
          "section_id": "sec-introduction-systemrelated-challenges-3c6a",
          "section_title": "System-Related Challenges",
          "targets": [
            {
              "target_section_id": "sec-conclusion-future-ml-systems-13b5",
              "target_section_title": "Future of ML Systems",
              "connection_type": "Preview",
              "similarity": 0.9090681672096252
            },
            {
              "target_section_id": "sec-conclusion-ethical-considerations-0219",
              "target_section_title": "Ethical Considerations",
              "connection_type": "Preview",
              "similarity": 0.8928587436676025
            }
          ]
        },
        {
          "section_id": "sec-introduction-ethical-considerations-5c13",
          "section_title": "Ethical Considerations",
          "targets": [
            {
              "target_section_id": "sec-conclusion-future-ml-systems-13b5",
              "target_section_title": "Future of ML Systems",
              "connection_type": "Preview",
              "similarity": 0.9348934292793274
            },
            {
              "target_section_id": "sec-conclusion-ethical-considerations-0219",
              "target_section_title": "Ethical Considerations",
              "connection_type": "Preview",
              "similarity": 0.9161177277565002
            },
            {
              "target_section_id": "sec-conclusion-security-privacy-a32e",
              "target_section_title": "Security and Privacy",
              "connection_type": "Preview",
              "similarity": 0.8821370005607605
            },
            {
              "target_section_id": "sec-conclusion-ai-hardware-advancements-9fdf",
              "target_section_title": "AI Hardware Advancements",
              "connection_type": "Preview",
              "similarity": 0.8707579970359802
            }
          ]
        },
        {
          "section_id": "sec-introduction-looking-ahead-532e",
          "section_title": "Looking Ahead",
          "targets": [
            {
              "target_section_id": "sec-conclusion-ethical-considerations-0219",
              "target_section_title": "Ethical Considerations",
              "connection_type": "Preview",
              "similarity": 0.9027497172355652
            },
            {
              "target_section_id": "sec-conclusion-future-ml-systems-13b5",
              "target_section_title": "Future of ML Systems",
              "connection_type": "Preview",
              "similarity": 0.8825267553329468
            }
          ]
        },
        {
          "section_id": "sec-introduction-book-structure-learning-path-411f",
          "section_title": "Book Structure and Learning Path",
          "targets": [
            {
              "target_section_id": "sec-conclusion-future-ml-systems-13b5",
              "target_section_title": "Future of ML Systems",
              "connection_type": "Preview",
              "similarity": 0.8918770551681519
            },
            {
              "target_section_id": "sec-conclusion-ai-hardware-advancements-9fdf",
              "target_section_title": "AI Hardware Advancements",
              "connection_type": "Preview",
              "similarity": 0.8823655247688293
            },
            {
              "target_section_id": "sec-conclusion-ml-training-basics-30d3",
              "target_section_title": "ML Training Basics",
              "connection_type": "Preview",
              "similarity": 0.8774406313896179
            },
            {
              "target_section_id": "sec-conclusion-ethical-considerations-0219",
              "target_section_title": "Ethical Considerations",
              "connection_type": "Preview",
              "similarity": 0.8724060654640198
            },
            {
              "target_section_id": "sec-conclusion-security-privacy-a32e",
              "target_section_title": "Security and Privacy",
              "connection_type": "Preview",
              "similarity": 0.8679475784301758
            }
          ]
        }
      ]
    },
    {
      "file": "conclusion.qmd",
      "sections": [
        {
          "section_id": "sec-conclusion-overview-fcb4",
          "section_title": "Overview",
          "targets": [
            {
              "target_section_id": "sec-introduction-ai-ml-basics-041a",
              "target_section_title": "AI and ML Basics",
              "connection_type": "Foundation",
              "similarity": 0.7420990467071533
            }
          ]
        },
        {
          "section_id": "sec-conclusion-ml-dataset-importance-e1af",
          "section_title": "ML Dataset Importance",
          "targets": [
            {
              "target_section_id": "sec-introduction-systemrelated-challenges-3c6a",
              "target_section_title": "System-Related Challenges",
              "connection_type": "Foundation",
              "similarity": 0.8547326922416687
            },
            {
              "target_section_id": "sec-introduction-ethical-considerations-5c13",
              "target_section_title": "Ethical Considerations",
              "connection_type": "Foundation",
              "similarity": 0.8526976108551025
            },
            {
              "target_section_id": "sec-introduction-datarelated-challenges-5b58",
              "target_section_title": "Data-Related Challenges",
              "connection_type": "Foundation",
              "similarity": 0.8355777859687805
            },
            {
              "target_section_id": "sec-introduction-ml-systems-wild-e270",
              "target_section_title": "ML Systems in the Wild",
              "connection_type": "Foundation",
              "similarity": 0.8207153081893921
            }
          ]
        },
        {
          "section_id": "sec-conclusion-ai-framework-navigation-042f",
          "section_title": "AI Framework Navigation",
          "targets": [
            {
              "target_section_id": "sec-introduction-ai-ml-basics-041a",
              "target_section_title": "AI and ML Basics",
              "connection_type": "Foundation",
              "similarity": 0.736764669418335
            }
          ]
        },
        {
          "section_id": "sec-conclusion-ml-training-basics-30d3",
          "section_title": "ML Training Basics",
          "targets": [
            {
              "target_section_id": "sec-introduction-book-structure-learning-path-411f",
              "target_section_title": "Book Structure and Learning Path",
              "connection_type": "Foundation",
              "similarity": 0.8774406313896179
            },
            {
              "target_section_id": "sec-introduction-modelrelated-challenges-ae5a",
              "target_section_title": "Model-Related Challenges",
              "connection_type": "Foundation",
              "similarity": 0.8597884774208069
            }
          ]
        },
        {
          "section_id": "sec-conclusion-ai-system-efficiency-b9e5",
          "section_title": "AI System Efficiency",
          "targets": [
            {
              "target_section_id": "sec-introduction-ai-ml-basics-041a",
              "target_section_title": "AI and ML Basics",
              "connection_type": "Foundation",
              "similarity": 0.8432511687278748
            }
          ]
        },
        {
          "section_id": "sec-conclusion-ai-hardware-advancements-9fdf",
          "section_title": "AI Hardware Advancements",
          "targets": [
            {
              "target_section_id": "sec-introduction-book-structure-learning-path-411f",
              "target_section_title": "Book Structure and Learning Path",
              "connection_type": "Foundation",
              "similarity": 0.8823655247688293
            },
            {
              "target_section_id": "sec-introduction-datarelated-challenges-5b58",
              "target_section_title": "Data-Related Challenges",
              "connection_type": "Foundation",
              "similarity": 0.8713963627815247
            },
            {
              "target_section_id": "sec-introduction-looking-ahead-532e",
              "target_section_title": "Looking Ahead",
              "connection_type": "Foundation",
              "similarity": 0.8712982535362244
            },
            {
              "target_section_id": "sec-introduction-ethical-considerations-5c13",
              "target_section_title": "Ethical Considerations",
              "connection_type": "Foundation",
              "similarity": 0.8707579970359802
            }
          ]
        },
        {
          "section_id": "sec-conclusion-ondevice-learning-0d33",
          "section_title": "On-Device Learning",
          "targets": [
            {
              "target_section_id": "sec-introduction-book-structure-learning-path-411f",
              "target_section_title": "Book Structure and Learning Path",
              "connection_type": "Foundation",
              "similarity": 0.8464952111244202
            },
            {
              "target_section_id": "sec-introduction-looking-ahead-532e",
              "target_section_title": "Looking Ahead",
              "connection_type": "Foundation",
              "similarity": 0.8444127440452576
            },
            {
              "target_section_id": "sec-introduction-ethical-considerations-5c13",
              "target_section_title": "Ethical Considerations",
              "connection_type": "Foundation",
              "similarity": 0.8437983989715576
            }
          ]
        },
        {
          "section_id": "sec-conclusion-security-privacy-a32e",
          "section_title": "Security and Privacy",
          "targets": [
            {
              "target_section_id": "sec-introduction-ethical-considerations-5c13",
              "target_section_title": "Ethical Considerations",
              "connection_type": "Foundation",
              "similarity": 0.8821370005607605
            },
            {
              "target_section_id": "sec-introduction-datarelated-challenges-5b58",
              "target_section_title": "Data-Related Challenges",
              "connection_type": "Foundation",
              "similarity": 0.8741453289985657
            },
            {
              "target_section_id": "sec-introduction-book-structure-learning-path-411f",
              "target_section_title": "Book Structure and Learning Path",
              "connection_type": "Foundation",
              "similarity": 0.8679475784301758
            }
          ]
        },
        {
          "section_id": "sec-conclusion-ethical-considerations-0219",
          "section_title": "Ethical Considerations",
          "targets": [
            {
              "target_section_id": "sec-introduction-ethical-considerations-5c13",
              "target_section_title": "Ethical Considerations",
              "connection_type": "Foundation",
              "similarity": 0.9161177277565002
            },
            {
              "target_section_id": "sec-introduction-looking-ahead-532e",
              "target_section_title": "Looking Ahead",
              "connection_type": "Foundation",
              "similarity": 0.9027497172355652
            },
            {
              "target_section_id": "sec-introduction-datarelated-challenges-5b58",
              "target_section_title": "Data-Related Challenges",
              "connection_type": "Foundation",
              "similarity": 0.900916576385498
            },
            {
              "target_section_id": "sec-introduction-systemrelated-challenges-3c6a",
              "target_section_title": "System-Related Challenges",
              "connection_type": "Foundation",
              "similarity": 0.8928587436676025
            },
            {
              "target_section_id": "sec-introduction-book-structure-learning-path-411f",
              "target_section_title": "Book Structure and Learning Path",
              "connection_type": "Foundation",
              "similarity": 0.8724060654640198
            }
          ]
        },
        {
          "section_id": "sec-conclusion-sustainability-9bc6",
          "section_title": "Sustainability",
          "targets": [
            {
              "target_section_id": "sec-introduction-modelrelated-challenges-ae5a",
              "target_section_title": "Model-Related Challenges",
              "connection_type": "Foundation",
              "similarity": 0.8181049823760986
            },
            {
              "target_section_id": "sec-model-optimizations-dynamic-computation-adaptation-8b9c",
              "target_section_title": "Dynamic Computation and Adaptation",
              "connection_type": "Foundation",
              "similarity": 0.7710362672805786
            },
            {
              "target_section_id": "sec-model-optimizations-practical-models-9344",
              "target_section_title": "Practical Models",
              "connection_type": "Foundation",
              "similarity": 0.7495510578155518
            },
            {
              "target_section_id": "sec-introduction-symbolic-ai-era-acc4",
              "target_section_title": "Symbolic AI Era",
              "connection_type": "Foundation",
              "similarity": 0.7452505826950073
            }
          ]
        },
        {
          "section_id": "sec-conclusion-robustness-resiliency-5623",
          "section_title": "Robustness and Resiliency",
          "targets": [
            {
              "target_section_id": "sec-introduction-book-structure-learning-path-411f",
              "target_section_title": "Book Structure and Learning Path",
              "connection_type": "Foundation",
              "similarity": 0.8486559391021729
            }
          ]
        },
        {
          "section_id": "sec-conclusion-future-ml-systems-13b5",
          "section_title": "Future of ML Systems",
          "targets": [
            {
              "target_section_id": "sec-introduction-ethical-considerations-5c13",
              "target_section_title": "Ethical Considerations",
              "connection_type": "Foundation",
              "similarity": 0.9348934292793274
            },
            {
              "target_section_id": "sec-introduction-datarelated-challenges-5b58",
              "target_section_title": "Data-Related Challenges",
              "connection_type": "Foundation",
              "similarity": 0.9257386922836304
            },
            {
              "target_section_id": "sec-introduction-systemrelated-challenges-3c6a",
              "target_section_title": "System-Related Challenges",
              "connection_type": "Foundation",
              "similarity": 0.9090681672096252
            },
            {
              "target_section_id": "sec-introduction-book-structure-learning-path-411f",
              "target_section_title": "Book Structure and Learning Path",
              "connection_type": "Foundation",
              "similarity": 0.8918770551681519
            },
            {
              "target_section_id": "sec-introduction-looking-ahead-532e",
              "target_section_title": "Looking Ahead",
              "connection_type": "Foundation",
              "similarity": 0.8825267553329468
            }
          ]
        },
        {
          "section_id": "sec-conclusion-ai-good-bb42",
          "section_title": "AI for Good",
          "targets": [
            {
              "target_section_id": "sec-introduction-ethical-considerations-5c13",
              "target_section_title": "Ethical Considerations",
              "connection_type": "Foundation",
              "similarity": 0.8296177387237549
            }
          ]
        },
        {
          "section_id": "sec-conclusion-congratulations-9028",
          "section_title": "Congratulations",
          "targets": [
            {
              "target_section_id": "sec-introduction-expert-systems-era-c061",
              "target_section_title": "Expert Systems Era",
              "connection_type": "Foundation",
              "similarity": 0.8154230117797852
            },
            {
              "target_section_id": "sec-introduction-book-structure-learning-path-411f",
              "target_section_title": "Book Structure and Learning Path",
              "connection_type": "Foundation",
              "similarity": 0.8064051866531372
            },
            {
              "target_section_id": "sec-introduction-ai-evolution-0dd8",
              "target_section_title": "AI Evolution",
              "connection_type": "Foundation",
              "similarity": 0.8028408885002136
            }
          ]
        }
      ]
    }
  ]
}