{
  "cross_references": {
    "sec-efficient-ai-overview-6f6a": [
      {
        "target_chapter": "introduction",
        "target_section": "sec-introduction-ai-pervasiveness-8891",
        "connection_type": "prerequisite_foundation",
        "cognitive_load": "low",
        "concepts": [
          "ai efficiency~ai evolution and history",
          "data efficiency~data quality assurance",
          "model compression~machine learning systems engineering",
          "resource optimization~power grid optimization",
          "performance trade-offs~performance monitoring"
        ],
        "strength": 1.832,
        "pedagogical_value": 1.0,
        "explanation": "Essential background: ai efficiency~ai evolution and history, data efficiency~data quality assurance, model compression~machine learning systems engineering and 5 more",
        "placement": "chapter_start",
        "priority": 1
      },
      {
        "target_chapter": "ml_systems",
        "target_section": "sec-ml-systems-overview-db10",
        "connection_type": "prerequisite_foundation",
        "cognitive_load": "low",
        "concepts": [
          "model compression",
          "recommendation systems",
          "environmental monitoring",
          "model quantization",
          "knowledge distillation"
        ],
        "strength": 2.4640000000000013,
        "pedagogical_value": 1.0,
        "explanation": "Essential background: model compression, recommendation systems, environmental monitoring and 5 more",
        "placement": "chapter_start",
        "priority": 1
      },
      {
        "target_chapter": "frameworks",
        "target_section": "sec-ai-frameworks-overview-f051",
        "connection_type": "conceptual_bridge",
        "cognitive_load": "medium",
        "concepts": [
          "edge computing",
          "tinyml systems",
          "real-time inference",
          "computer vision",
          "natural language processing"
        ],
        "strength": 2.2730000000000006,
        "pedagogical_value": 0.9,
        "explanation": "Related concepts: edge computing, tinyml systems, real-time inference and 5 more",
        "placement": "section_transition",
        "priority": 2
      },
      {
        "target_chapter": "optimizations",
        "target_section": "sec-model-optimizations-overview-b523",
        "connection_type": "conceptual_bridge",
        "cognitive_load": "medium",
        "concepts": [
          "model compression",
          "mobile ai applications",
          "real-time inference",
          "computer vision",
          "natural language processing"
        ],
        "strength": 2.6930000000000023,
        "pedagogical_value": 0.9,
        "explanation": "Related concepts: model compression, mobile ai applications, real-time inference and 5 more",
        "placement": "section_transition",
        "priority": 2
      },
      {
        "target_chapter": "hw_acceleration",
        "target_section": "sec-ai-acceleration-overview-47d1",
        "connection_type": "conceptual_bridge",
        "cognitive_load": "medium",
        "concepts": [
          "computer vision",
          "natural language processing",
          "scientific computing",
          "energy efficiency",
          "ai efficiency~energy efficiency"
        ],
        "strength": 2.4400000000000004,
        "pedagogical_value": 0.9,
        "explanation": "Related concepts: computer vision, natural language processing, scientific computing and 5 more",
        "placement": "section_transition",
        "priority": 2
      }
    ],
    "sec-efficient-ai-ai-scaling-laws-a043": [
      {
        "target_chapter": "introduction",
        "target_section": "sec-introduction-ai-pervasiveness-8891",
        "connection_type": "prerequisite_foundation",
        "cognitive_load": "low",
        "concepts": [
          "ai efficiency~ai evolution and history",
          "data efficiency~data quality assurance",
          "model compression~machine learning systems engineering",
          "resource optimization~power grid optimization",
          "performance trade-offs~performance monitoring"
        ],
        "strength": 1.832,
        "pedagogical_value": 1.0,
        "explanation": "Essential background: ai efficiency~ai evolution and history, data efficiency~data quality assurance, model compression~machine learning systems engineering and 5 more",
        "placement": "chapter_start",
        "priority": 1
      },
      {
        "target_chapter": "ml_systems",
        "target_section": "sec-ml-systems-overview-db10",
        "connection_type": "prerequisite_foundation",
        "cognitive_load": "low",
        "concepts": [
          "model compression",
          "recommendation systems",
          "environmental monitoring",
          "model quantization",
          "knowledge distillation"
        ],
        "strength": 2.4640000000000013,
        "pedagogical_value": 1.0,
        "explanation": "Essential background: model compression, recommendation systems, environmental monitoring and 5 more",
        "placement": "chapter_start",
        "priority": 1
      },
      {
        "target_chapter": "frameworks",
        "target_section": "sec-ai-frameworks-overview-f051",
        "connection_type": "conceptual_bridge",
        "cognitive_load": "medium",
        "concepts": [
          "edge computing",
          "tinyml systems",
          "real-time inference",
          "computer vision",
          "natural language processing"
        ],
        "strength": 2.2730000000000006,
        "pedagogical_value": 0.9,
        "explanation": "Related concepts: edge computing, tinyml systems, real-time inference and 5 more",
        "placement": "section_transition",
        "priority": 2
      },
      {
        "target_chapter": "optimizations",
        "target_section": "sec-model-optimizations-overview-b523",
        "connection_type": "conceptual_bridge",
        "cognitive_load": "medium",
        "concepts": [
          "model compression",
          "mobile ai applications",
          "real-time inference",
          "computer vision",
          "natural language processing"
        ],
        "strength": 2.6930000000000023,
        "pedagogical_value": 0.9,
        "explanation": "Related concepts: model compression, mobile ai applications, real-time inference and 5 more",
        "placement": "section_transition",
        "priority": 2
      }
    ],
    "sec-efficient-ai-pillars-ai-efficiency-c024": [
      {
        "target_chapter": "introduction",
        "target_section": "sec-introduction-ai-pervasiveness-8891",
        "connection_type": "prerequisite_foundation",
        "cognitive_load": "low",
        "concepts": [
          "ai efficiency~ai evolution and history",
          "data efficiency~data quality assurance",
          "model compression~machine learning systems engineering",
          "resource optimization~power grid optimization",
          "performance trade-offs~performance monitoring"
        ],
        "strength": 1.832,
        "pedagogical_value": 1.0,
        "explanation": "Essential background: ai efficiency~ai evolution and history, data efficiency~data quality assurance, model compression~machine learning systems engineering and 5 more",
        "placement": "chapter_start",
        "priority": 1
      },
      {
        "target_chapter": "ml_systems",
        "target_section": "sec-ml-systems-overview-db10",
        "connection_type": "prerequisite_foundation",
        "cognitive_load": "low",
        "concepts": [
          "model compression",
          "recommendation systems",
          "environmental monitoring",
          "model quantization",
          "knowledge distillation"
        ],
        "strength": 2.4640000000000013,
        "pedagogical_value": 1.0,
        "explanation": "Essential background: model compression, recommendation systems, environmental monitoring and 5 more",
        "placement": "chapter_start",
        "priority": 1
      },
      {
        "target_chapter": "frameworks",
        "target_section": "sec-ai-frameworks-overview-f051",
        "connection_type": "conceptual_bridge",
        "cognitive_load": "medium",
        "concepts": [
          "edge computing",
          "tinyml systems",
          "real-time inference",
          "computer vision",
          "natural language processing"
        ],
        "strength": 2.2730000000000006,
        "pedagogical_value": 0.9,
        "explanation": "Related concepts: edge computing, tinyml systems, real-time inference and 5 more",
        "placement": "section_transition",
        "priority": 2
      },
      {
        "target_chapter": "optimizations",
        "target_section": "sec-model-optimizations-overview-b523",
        "connection_type": "conceptual_bridge",
        "cognitive_load": "medium",
        "concepts": [
          "model compression",
          "mobile ai applications",
          "real-time inference",
          "computer vision",
          "natural language processing"
        ],
        "strength": 2.6930000000000023,
        "pedagogical_value": 0.9,
        "explanation": "Related concepts: model compression, mobile ai applications, real-time inference and 5 more",
        "placement": "section_transition",
        "priority": 2
      }
    ],
    "sec-efficient-ai-system-efficiency-3cf1": [
      {
        "target_chapter": "introduction",
        "target_section": "sec-introduction-ai-pervasiveness-8891",
        "connection_type": "prerequisite_foundation",
        "cognitive_load": "low",
        "concepts": [
          "ai efficiency~ai evolution and history",
          "data efficiency~data quality assurance",
          "model compression~machine learning systems engineering",
          "resource optimization~power grid optimization",
          "performance trade-offs~performance monitoring"
        ],
        "strength": 1.832,
        "pedagogical_value": 1.0,
        "explanation": "Essential background: ai efficiency~ai evolution and history, data efficiency~data quality assurance, model compression~machine learning systems engineering and 5 more",
        "placement": "chapter_start",
        "priority": 1
      },
      {
        "target_chapter": "ml_systems",
        "target_section": "sec-ml-systems-overview-db10",
        "connection_type": "prerequisite_foundation",
        "cognitive_load": "low",
        "concepts": [
          "model compression",
          "recommendation systems",
          "environmental monitoring",
          "model quantization",
          "knowledge distillation"
        ],
        "strength": 2.4640000000000013,
        "pedagogical_value": 1.0,
        "explanation": "Essential background: model compression, recommendation systems, environmental monitoring and 5 more",
        "placement": "chapter_start",
        "priority": 1
      },
      {
        "target_chapter": "frameworks",
        "target_section": "sec-ai-frameworks-overview-f051",
        "connection_type": "conceptual_bridge",
        "cognitive_load": "medium",
        "concepts": [
          "edge computing",
          "tinyml systems",
          "real-time inference",
          "computer vision",
          "natural language processing"
        ],
        "strength": 2.2730000000000006,
        "pedagogical_value": 0.9,
        "explanation": "Related concepts: edge computing, tinyml systems, real-time inference and 5 more",
        "placement": "section_transition",
        "priority": 2
      },
      {
        "target_chapter": "optimizations",
        "target_section": "sec-model-optimizations-overview-b523",
        "connection_type": "conceptual_bridge",
        "cognitive_load": "medium",
        "concepts": [
          "model compression",
          "mobile ai applications",
          "real-time inference",
          "computer vision",
          "natural language processing"
        ],
        "strength": 2.6930000000000023,
        "pedagogical_value": 0.9,
        "explanation": "Related concepts: model compression, mobile ai applications, real-time inference and 5 more",
        "placement": "section_transition",
        "priority": 2
      }
    ],
    "sec-efficient-ai-efficiency-tradeoffs-challenges-946d": [
      {
        "target_chapter": "introduction",
        "target_section": "sec-introduction-ai-pervasiveness-8891",
        "connection_type": "prerequisite_foundation",
        "cognitive_load": "low",
        "concepts": [
          "ai efficiency~ai evolution and history",
          "data efficiency~data quality assurance",
          "model compression~machine learning systems engineering",
          "resource optimization~power grid optimization",
          "performance trade-offs~performance monitoring"
        ],
        "strength": 1.832,
        "pedagogical_value": 1.0,
        "explanation": "Essential background: ai efficiency~ai evolution and history, data efficiency~data quality assurance, model compression~machine learning systems engineering and 5 more",
        "placement": "chapter_start",
        "priority": 1
      },
      {
        "target_chapter": "ml_systems",
        "target_section": "sec-ml-systems-overview-db10",
        "connection_type": "prerequisite_foundation",
        "cognitive_load": "low",
        "concepts": [
          "model compression",
          "recommendation systems",
          "environmental monitoring",
          "model quantization",
          "knowledge distillation"
        ],
        "strength": 2.4640000000000013,
        "pedagogical_value": 1.0,
        "explanation": "Essential background: model compression, recommendation systems, environmental monitoring and 5 more",
        "placement": "chapter_start",
        "priority": 1
      },
      {
        "target_chapter": "frameworks",
        "target_section": "sec-ai-frameworks-overview-f051",
        "connection_type": "conceptual_bridge",
        "cognitive_load": "medium",
        "concepts": [
          "edge computing",
          "tinyml systems",
          "real-time inference",
          "computer vision",
          "natural language processing"
        ],
        "strength": 2.2730000000000006,
        "pedagogical_value": 0.9,
        "explanation": "Related concepts: edge computing, tinyml systems, real-time inference and 5 more",
        "placement": "section_transition",
        "priority": 2
      },
      {
        "target_chapter": "optimizations",
        "target_section": "sec-model-optimizations-overview-b523",
        "connection_type": "conceptual_bridge",
        "cognitive_load": "medium",
        "concepts": [
          "model compression",
          "mobile ai applications",
          "real-time inference",
          "computer vision",
          "natural language processing"
        ],
        "strength": 2.6930000000000023,
        "pedagogical_value": 0.9,
        "explanation": "Related concepts: model compression, mobile ai applications, real-time inference and 5 more",
        "placement": "section_transition",
        "priority": 2
      }
    ],
    "sec-efficient-ai-managing-tradeoffs-80e8": [
      {
        "target_chapter": "introduction",
        "target_section": "sec-introduction-ai-pervasiveness-8891",
        "connection_type": "prerequisite_foundation",
        "cognitive_load": "low",
        "concepts": [
          "ai efficiency~ai evolution and history",
          "data efficiency~data quality assurance",
          "model compression~machine learning systems engineering",
          "resource optimization~power grid optimization",
          "performance trade-offs~performance monitoring"
        ],
        "strength": 1.832,
        "pedagogical_value": 1.0,
        "explanation": "Essential background: ai efficiency~ai evolution and history, data efficiency~data quality assurance, model compression~machine learning systems engineering and 5 more",
        "placement": "chapter_start",
        "priority": 1
      },
      {
        "target_chapter": "ml_systems",
        "target_section": "sec-ml-systems-overview-db10",
        "connection_type": "prerequisite_foundation",
        "cognitive_load": "low",
        "concepts": [
          "model compression",
          "recommendation systems",
          "environmental monitoring",
          "model quantization",
          "knowledge distillation"
        ],
        "strength": 2.4640000000000013,
        "pedagogical_value": 1.0,
        "explanation": "Essential background: model compression, recommendation systems, environmental monitoring and 5 more",
        "placement": "chapter_start",
        "priority": 1
      },
      {
        "target_chapter": "frameworks",
        "target_section": "sec-ai-frameworks-overview-f051",
        "connection_type": "conceptual_bridge",
        "cognitive_load": "medium",
        "concepts": [
          "edge computing",
          "tinyml systems",
          "real-time inference",
          "computer vision",
          "natural language processing"
        ],
        "strength": 2.2730000000000006,
        "pedagogical_value": 0.9,
        "explanation": "Related concepts: edge computing, tinyml systems, real-time inference and 5 more",
        "placement": "section_transition",
        "priority": 2
      },
      {
        "target_chapter": "optimizations",
        "target_section": "sec-model-optimizations-overview-b523",
        "connection_type": "conceptual_bridge",
        "cognitive_load": "medium",
        "concepts": [
          "model compression",
          "mobile ai applications",
          "real-time inference",
          "computer vision",
          "natural language processing"
        ],
        "strength": 2.6930000000000023,
        "pedagogical_value": 0.9,
        "explanation": "Related concepts: model compression, mobile ai applications, real-time inference and 5 more",
        "placement": "section_transition",
        "priority": 2
      }
    ],
    "sec-efficient-ai-efficiencyfirst-mindset-39e7": [
      {
        "target_chapter": "introduction",
        "target_section": "sec-introduction-ai-pervasiveness-8891",
        "connection_type": "prerequisite_foundation",
        "cognitive_load": "low",
        "concepts": [
          "ai efficiency~ai evolution and history",
          "data efficiency~data quality assurance",
          "model compression~machine learning systems engineering",
          "resource optimization~power grid optimization",
          "performance trade-offs~performance monitoring"
        ],
        "strength": 1.832,
        "pedagogical_value": 1.0,
        "explanation": "Essential background: ai efficiency~ai evolution and history, data efficiency~data quality assurance, model compression~machine learning systems engineering and 5 more",
        "placement": "chapter_start",
        "priority": 1
      },
      {
        "target_chapter": "ml_systems",
        "target_section": "sec-ml-systems-overview-db10",
        "connection_type": "prerequisite_foundation",
        "cognitive_load": "low",
        "concepts": [
          "model compression",
          "recommendation systems",
          "environmental monitoring",
          "model quantization",
          "knowledge distillation"
        ],
        "strength": 2.4640000000000013,
        "pedagogical_value": 1.0,
        "explanation": "Essential background: model compression, recommendation systems, environmental monitoring and 5 more",
        "placement": "chapter_start",
        "priority": 1
      },
      {
        "target_chapter": "frameworks",
        "target_section": "sec-ai-frameworks-overview-f051",
        "connection_type": "conceptual_bridge",
        "cognitive_load": "medium",
        "concepts": [
          "edge computing",
          "tinyml systems",
          "real-time inference",
          "computer vision",
          "natural language processing"
        ],
        "strength": 2.2730000000000006,
        "pedagogical_value": 0.9,
        "explanation": "Related concepts: edge computing, tinyml systems, real-time inference and 5 more",
        "placement": "section_transition",
        "priority": 2
      },
      {
        "target_chapter": "optimizations",
        "target_section": "sec-model-optimizations-overview-b523",
        "connection_type": "conceptual_bridge",
        "cognitive_load": "medium",
        "concepts": [
          "model compression",
          "mobile ai applications",
          "real-time inference",
          "computer vision",
          "natural language processing"
        ],
        "strength": 2.6930000000000023,
        "pedagogical_value": 0.9,
        "explanation": "Related concepts: model compression, mobile ai applications, real-time inference and 5 more",
        "placement": "section_transition",
        "priority": 2
      }
    ],
    "sec-efficient-ai-broader-challenges-fe2d": [
      {
        "target_chapter": "introduction",
        "target_section": "sec-introduction-ai-pervasiveness-8891",
        "connection_type": "prerequisite_foundation",
        "cognitive_load": "low",
        "concepts": [
          "ai efficiency~ai evolution and history",
          "data efficiency~data quality assurance",
          "model compression~machine learning systems engineering",
          "resource optimization~power grid optimization",
          "performance trade-offs~performance monitoring"
        ],
        "strength": 1.832,
        "pedagogical_value": 1.0,
        "explanation": "Essential background: ai efficiency~ai evolution and history, data efficiency~data quality assurance, model compression~machine learning systems engineering and 5 more",
        "placement": "chapter_start",
        "priority": 1
      },
      {
        "target_chapter": "ml_systems",
        "target_section": "sec-ml-systems-overview-db10",
        "connection_type": "prerequisite_foundation",
        "cognitive_load": "low",
        "concepts": [
          "model compression",
          "recommendation systems",
          "environmental monitoring",
          "model quantization",
          "knowledge distillation"
        ],
        "strength": 2.4640000000000013,
        "pedagogical_value": 1.0,
        "explanation": "Essential background: model compression, recommendation systems, environmental monitoring and 5 more",
        "placement": "chapter_start",
        "priority": 1
      },
      {
        "target_chapter": "frameworks",
        "target_section": "sec-ai-frameworks-overview-f051",
        "connection_type": "conceptual_bridge",
        "cognitive_load": "medium",
        "concepts": [
          "edge computing",
          "tinyml systems",
          "real-time inference",
          "computer vision",
          "natural language processing"
        ],
        "strength": 2.2730000000000006,
        "pedagogical_value": 0.9,
        "explanation": "Related concepts: edge computing, tinyml systems, real-time inference and 5 more",
        "placement": "section_transition",
        "priority": 2
      },
      {
        "target_chapter": "optimizations",
        "target_section": "sec-model-optimizations-overview-b523",
        "connection_type": "conceptual_bridge",
        "cognitive_load": "medium",
        "concepts": [
          "model compression",
          "mobile ai applications",
          "real-time inference",
          "computer vision",
          "natural language processing"
        ],
        "strength": 2.6930000000000023,
        "pedagogical_value": 0.9,
        "explanation": "Related concepts: model compression, mobile ai applications, real-time inference and 5 more",
        "placement": "section_transition",
        "priority": 2
      }
    ],
    "sec-efficient-ai-summary-66bb": [
      {
        "target_chapter": "introduction",
        "target_section": "sec-introduction-ai-pervasiveness-8891",
        "connection_type": "prerequisite_foundation",
        "cognitive_load": "low",
        "concepts": [
          "ai efficiency~ai evolution and history",
          "data efficiency~data quality assurance",
          "model compression~machine learning systems engineering",
          "resource optimization~power grid optimization",
          "performance trade-offs~performance monitoring"
        ],
        "strength": 1.832,
        "pedagogical_value": 1.0,
        "explanation": "Essential background: ai efficiency~ai evolution and history, data efficiency~data quality assurance, model compression~machine learning systems engineering and 5 more",
        "placement": "chapter_start",
        "priority": 1
      },
      {
        "target_chapter": "ml_systems",
        "target_section": "sec-ml-systems-overview-db10",
        "connection_type": "prerequisite_foundation",
        "cognitive_load": "low",
        "concepts": [
          "model compression",
          "recommendation systems",
          "environmental monitoring",
          "model quantization",
          "knowledge distillation"
        ],
        "strength": 2.4640000000000013,
        "pedagogical_value": 1.0,
        "explanation": "Essential background: model compression, recommendation systems, environmental monitoring and 5 more",
        "placement": "chapter_start",
        "priority": 1
      },
      {
        "target_chapter": "frameworks",
        "target_section": "sec-ai-frameworks-overview-f051",
        "connection_type": "conceptual_bridge",
        "cognitive_load": "medium",
        "concepts": [
          "edge computing",
          "tinyml systems",
          "real-time inference",
          "computer vision",
          "natural language processing"
        ],
        "strength": 2.2730000000000006,
        "pedagogical_value": 0.9,
        "explanation": "Related concepts: edge computing, tinyml systems, real-time inference and 5 more",
        "placement": "section_transition",
        "priority": 2
      },
      {
        "target_chapter": "optimizations",
        "target_section": "sec-model-optimizations-overview-b523",
        "connection_type": "conceptual_bridge",
        "cognitive_load": "medium",
        "concepts": [
          "model compression",
          "mobile ai applications",
          "real-time inference",
          "computer vision",
          "natural language processing"
        ],
        "strength": 2.6930000000000023,
        "pedagogical_value": 0.9,
        "explanation": "Related concepts: model compression, mobile ai applications, real-time inference and 5 more",
        "placement": "section_transition",
        "priority": 2
      },
      {
        "target_chapter": "hw_acceleration",
        "target_section": "sec-ai-acceleration-overview-47d1",
        "connection_type": "conceptual_bridge",
        "cognitive_load": "medium",
        "concepts": [
          "computer vision",
          "natural language processing",
          "scientific computing",
          "energy efficiency",
          "ai efficiency~energy efficiency"
        ],
        "strength": 2.4400000000000004,
        "pedagogical_value": 0.9,
        "explanation": "Related concepts: computer vision, natural language processing, scientific computing and 5 more",
        "placement": "section_transition",
        "priority": 2
      }
    ]
  },
  "generated_date": "2025-09-12",
  "generator": "cognitive_load_optimized_generator.py",
  "version": "1.0",
  "optimization_approach": "cognitive_load_theory",
  "total_connections": 38
}